upbit/__init__.py
upbit/exceptions.py
upbit/models.py
upbit/upbit.py
python_upbit_api-1.9.1.dist-info/LICENSE
python_upbit_api-1.9.1.dist-info/METADATA
python_upbit_api-1.9.1.dist-info/WHEEL
python_upbit_api-1.9.1.dist-info/top_level.txt
python_upbit_api-1.9.1.dist-info/RECORD
