Metadata-Version: 2.1
Name: python-upbit-api
Version: 1.9.1
Summary: Python Upbit API Wrapper
Author-email: 이지혜 Lee Jihye <ghe.lee19@gmail.com>
Maintainer-email: 이지혜 Lee Jihye <ghe.lee19@gmail.com>
License: MIT License
Project-URL: homepage, https://github.com/designmeme/python-upbit-api
Project-URL: repository, https://github.com/designmeme/python-upbit-api.git
Project-URL: changelog, https://github.com/designmeme/python-upbit-api/blob/main/CHANGELOG.md
Project-URL: issues, https://github.com/designmeme/python-upbit-api/issues
Classifier: Development Status :: 5 - Production/Stable
Classifier: Programming Language :: Python
Classifier: Programming Language :: Python :: 3
Classifier: Programming Language :: Python :: 3.8
Classifier: Programming Language :: Python :: 3.9
Classifier: Programming Language :: Python :: 3.10
Classifier: Programming Language :: Python :: 3.11
Classifier: License :: OSI Approved :: MIT License
Classifier: Operating System :: OS Independent
Requires-Python: >=3.8
License-File: LICENSE
Requires-Dist: requests >=2.0.0
Requires-Dist: urllib3 >=1.0.0
Requires-Dist: pyjwt >=2.0.0
